{
  "_fv": 13,
  "_type": "recipe",
  "definition": {
    "recipeType": "Crafting",
    "xpReward": 0.0,
    "cookingTime": 200,
    "recipeRetstackSize": 1,
    "group": "",
    "recipeShapeless": true,
    "recipeSlots": [
      {
        "value": "CUSTOM:EmeraldShovel"
      },
      {
        "value": "CUSTOM:EmeraldPickaxe"
      },
      {
        "value": "CUSTOM:EmeraldAxe"
      },
      {
        "value": "CUSTOM:EmeraldHoe"
      },
      {
        "value": "Items.SHEARS"
      },
      {
        "value": ""
      },
      {
        "value": ""
      },
      {
        "value": ""
      },
      {
        "value": ""
      }
    ],
    "recipeReturnStack": {
      "value": "CUSTOM:EmeraldMultitool"
    },
    "name": "emerald_multi_tool_recipe",
    "namespace": "mod"
  }
}